package/__init__.py
package/main.py
sklinks05-0.1.dist-info/LICENCE.text
sklinks05-0.1.dist-info/METADATA
sklinks05-0.1.dist-info/WHEEL
sklinks05-0.1.dist-info/top_level.txt
sklinks05-0.1.dist-info/RECORD
