Metadata-Version: 2.1
Name: sklinks05
Version: 0.1
Summary: This is a package
Author: UNKNOWN XR
Author-email: xxxjack2018@gmail.com
Classifier: Programming Language :: Python :: 3
Classifier: License :: OSI Approved :: MIT License
Classifier: Operating System :: OS Independent
License-File: LICENCE.text
